partx/__init__.py
partx/continued_sampling.py
partx/controlled_budget.py
partx/models.py
partx/part_optimize.py
partx/partitioning.py
partx/py.typed
partx-0.1.2.dist-info/WHEEL
partx-0.1.2.dist-info/METADATA
partx-0.1.2.dist-info/RECORD
