Metadata-Version: 2.1
Name: partx
Version: 0.1.2
Summary: PartX Optimizer to use with PSY-Taliro
License: MIT
Author: Aniruddh Chandratre
Author-email: achand75@asu.edu
Requires-Python: >=3.7.1,<3.10
Classifier: License :: OSI Approved :: MIT License
Classifier: Programming Language :: Python :: 3
Classifier: Programming Language :: Python :: 3.8
Classifier: Programming Language :: Python :: 3.9
Requires-Dist: bokeh (>=2.3.2,<3.0.0)
Requires-Dist: matplotlib (>=3.4.2,<4.0.0)
Requires-Dist: numpy (>=1.20.3,<2.0.0)
Requires-Dist: pandas (>=1.2.4,<2.0.0)
Requires-Dist: pathos (>=0.2.8,<0.3.0)
Requires-Dist: psy-taliro (>=1.0.0a4,<2.0.0)
Requires-Dist: scikit-learn (>=0.24.2,<0.25.0)
Requires-Dist: scipy (>=1.6.3,<2.0.0)
